setup.py
Directory_Caching.egg-info/PKG-INFO
Directory_Caching.egg-info/SOURCES.txt
Directory_Caching.egg-info/dependency_links.txt
Directory_Caching.egg-info/top_level.txt
directory_caching/__init__.py
directory_caching/archives.py
directory_caching.egg-info/SOURCES.txt
tools/force_dependency_upgrades.sh