Metadata-Version: 1.1
Name: directory-caching
Version: 1.12
Summary: Simple and basic Directory Listing, File information, & Zip File Listings Caching.
Home-page: https://github.com/bschollnick/Directory_Caching/tree/master
Author: Benjamin Schollnick
Author-email: Benjamin@schollnick.net
License: UNKNOWN
Download-URL: https://github.com/bschollnick/Directory_Caching/tree/master
Keywords: caching files directories scandir naturalsort
Platform: UNKNOWN
Classifier: Development Status :: 5 - Production/Stable
Classifier: Intended Audience :: Developers
Classifier: Operating System :: MacOS :: MacOS X
Classifier: Operating System :: Microsoft :: Windows :: Windows 7
Classifier: Operating System :: Microsoft :: Windows :: Windows XP
Classifier: Operating System :: POSIX :: Linux
Classifier: Programming Language :: Python :: 2
Requires: natsort
Requires: scandir
